fastpredict/__init__.py
fastpredict/predict.py
fastpredict-0.0.6.dist-info/LICENSE
fastpredict-0.0.6.dist-info/METADATA
fastpredict-0.0.6.dist-info/WHEEL
fastpredict-0.0.6.dist-info/top_level.txt
fastpredict-0.0.6.dist-info/RECORD
