Metadata-Version: 2.1
Name: fastpredict
Version: 0.0.6
Summary: A few helper utilities to make it simpler to perform fastai inference/prediction
Home-page: https://github.com/kapily/fastpredict
Author: Kapil Yedidi
Author-email: kapily.code@gmail.com
License: UNKNOWN
Platform: UNKNOWN
Classifier: Programming Language :: Python :: 3
Classifier: License :: OSI Approved :: MIT License
Classifier: Operating System :: OS Independent
Requires-Python: >=3.0
Requires-Dist: fastai (>=2.1.10)
Requires-Dist: python-magic (>=0.4.18)
